azure/cli/telemetry/__init__.py
azure/cli/telemetry/const.py
azure/cli/telemetry/util.py
azure/cli/telemetry/components/__init__.py
azure/cli/telemetry/components/records_collection.py
azure/cli/telemetry/components/telemetry_client.py
azure/cli/telemetry/components/telemetry_logging.py
azure/cli/telemetry/components/telemetry_note.py
azure_cli_telemetry-1.1.0.post20250227030620.dist-info/LICENSE.txt
azure_cli_telemetry-1.1.0.post20250227030620.dist-info/METADATA
azure_cli_telemetry-1.1.0.post20250227030620.dist-info/WHEEL
azure_cli_telemetry-1.1.0.post20250227030620.dist-info/top_level.txt
azure_cli_telemetry-1.1.0.post20250227030620.dist-info/RECORD
