Metadata-Version: 2.2
Name: azure-cli-telemetry
Version: 1.1.0.post20250227030620
Summary: Microsoft Azure CLI Telemetry Package
Home-page: https://github.com/Azure/azure-cli
Author: Microsoft Corporation
Author-email: azpycli@microsoft.com
License: MIT
Classifier: Development Status :: 5 - Production/Stable
Classifier: Intended Audience :: Developers
Classifier: Intended Audience :: System Administrators
Classifier: Programming Language :: Python
Classifier: Programming Language :: Python :: 3
Classifier: Programming Language :: Python :: 3.8
Classifier: Programming Language :: Python :: 3.9
Classifier: Programming Language :: Python :: 3.10
Classifier: Programming Language :: Python :: 3.11
Classifier: Programming Language :: Python :: 3.12
Classifier: License :: OSI Approved :: MIT License
License-File: LICENSE.txt
Requires-Dist: applicationinsights<0.12,>=0.11.1
Requires-Dist: portalocker<3,>=1.6
Dynamic: author
Dynamic: author-email
Dynamic: classifier
Dynamic: description
Dynamic: home-page
Dynamic: license
Dynamic: requires-dist
Dynamic: summary
